LICENSE.txt
MANIFEST.in
README.rst
setup.py
eulerlib/__init__.py
eulerlib/_exceptions.py
eulerlib/etc.py
eulerlib/fibonacci.py
eulerlib/numtheory.py
eulerlib/prime_numbers.py
eulerlib/pythagoras.py
eulerlib.egg-info/PKG-INFO
eulerlib.egg-info/SOURCES.txt
eulerlib.egg-info/dependency_links.txt
eulerlib.egg-info/not-zip-safe
eulerlib.egg-info/top_level.txt