Metadata-Version: 1.1
Name: eulerlib
Version: 0.2
Summary: A library of number theory related functions inspired by Project Euler.
Home-page: https://bitbucket.org/transmogrifier/eulerlib
Author: Sameer Marathe
Author-email: transmogrifier@gmail.com
License: Apache License 2.0
Keywords: mathematics project_euler number_theory prime_numbers
Platform: UNKNOWN
Classifier: Development Status :: 4 - Beta
Classifier: License :: OSI Approved :: Apache Software License
Classifier: Programming Language :: Python :: 2.7
Classifier: Programming Language :: Python :: 3.4
Classifier: Topic :: Scientific/Engineering :: Mathematics
Classifier: Intended Audience :: Developers
Classifier: Intended Audience :: Science/Research
Classifier: Intended Audience :: End Users/Desktop
